{"version": "v3.0.4 Beta", "title": "Static Analysis", "file_name": "com.twitter.android.apk", "app_name": "Twitter", "app_type": "apk", "size": "31.03MB", "md5": "16d84d2e9e6627faf4f257668bcb7282", "sha1": "8ada40a5df0828c3b7350c7b16cd63212bedbf07", "sha256": "79735a5c2fd43ae75a3135fb56d6be1861148d142d7ee12bbb72d8b64810ac87", "package_name": "com.twitter.android", "main_activity": "com.twitter.android.StartActivity", "activities": ["com.twitter.android.LoginActivity", "com.twitter.android.LoginChallengeActivity", "com.twitter.android.profilecompletionmodule.ProfileCompletionFlowActivity", "com.twitter.android.PasswordResetActivity", "com.twitter.android.settings.NotificationSettingsActivity", "com.twitter.app.safety.notificationfilters.NotificationFiltersSettingsActivity", "com.twitter.android.AdvancedDiscoSettingsActivity", "com.twitter.android.ChangeScreenNameActivity", "com.twitter.app.main.MainActivity", "com.twitter.app.users.UsersActivity", "com.twitter.android.BlockedAccountsActivity", "com.twitter.android.ChangePasswordActivity", "com.twitter.android.smartfollow.interestsearch.InterestSearchActivity", "com.twitter.app.lists.ListsActivity", "com.twitter.android.account.teamsaccountswitcher.TeamsAccountSwitcherActivity", "com.twitter.android.TotpGeneratorActivity", "com.twitter.android.BackupCodeActivity", "com.twitter.android.TemporaryAppPasswordActivity", "com.twitter.android.LoginVerificationActivity", "com.twitter.app.lists.ListTabActivity", "com.twitter.android.TabbedVitFollowersActivity", "com.twitter.android.search.SearchActivity", "com.twitter.android.search.SearchFieldActivity", "com.twitter.android.search.AdvancedSearchFiltersActivity", "com.twitter.android.search.SearchSettingsActivity", "com.twitter.android.revenue.brandsurvey.BrandSurveyQuestionActivity", "com.twitter.app.lists.ListCreateEditActivity", "com.twitter.composer.ComposerActivity", "com.twitter.android.GalleryGridActivity", "com.twitter.android.media.foundmedia.GifCategoriesActivity", "com.twitter.android.media.foundmedia.GifGalleryActivity", "com.twitter.android.media.foundmedia.GifPreviewActivity", "com.twitter.android.ConnectContactsUploadHelperActivity", "com.twitter.android.people.PeopleDiscoveryActivity", "com.twitter.android.revenue.CampaignTimelineActivity", "com.twitter.android.liveevent.landing.LiveEventLandingActivity", "com.twitter.android.TweetDetailActivity", "com.twitter.android.RootTweetDetailActivity", "com.twitter.app.dm.RootDMActivity", "com.twitter.app.dm.DMActivity", "com.twitter.app.dm.DMRequestsActivity", "com.twitter.android.settings.dm.DMSettingsActivity", "com.twitter.app.dm.DMConversationSettingsActivity", "com.twitter.app.dm.SecretDMShowKeysActivity", "com.twitter.app.dm.GroupInfoEditActivity", "com.twitter.app.dm.DMViewGroupParticipantsActivity", "com.twitter.app.dm.DMAvatarFullViewActivity", "com.twitter.android.EditProfileActivity", "com.twitter.android.EditProfileAvatarActivity", "com.twitter.android.ProfilePhotoImageActivity", "com.twitter.app.dm.cards.dmfeedbackcard.FeedbackEnterCommentActivity", "com.twitter.android.EditBirthdateActivity", "com.twitter.android.ProfileActivity", "com.twitter.android.ProfilePhotoPromptActivity", "com.twitter.android.dialog.NotifyRetweetDialogFragmentActivity", "com.twitter.android.dialog.PhoneVerificationDialogFragmentActivity", "com.twitter.android.dialog.RateLimitDialogFragmentActivity", "com.twitter.android.dialog.AgeGateDialogFragmentActivity", "com.twitter.android.dialog.LoggedOutSettingDialogFragmentActivity", "com.twitter.android.dialog.UpdatePhoneDialogActivity", "com.twitter.android.dialog.FollowingExceededDialogFragmentActivity", "com.twitter.android.DialogActivity", "com.twitter.android.PhoneEntrySettingsActivity", "com.twitter.android.AddUpdateEmailActivity", "com.twitter.android.PhoneVerifySettingsActivity", "com.twitter.android.PhoneMTFlowActivity", "com.twitter.android.PhoneOwnershipActivity", "com.twitter.app.users.AddressbookContactsActivity", "com.twitter.android.ImageActivity", "com.twitter.android.WebViewActivity", "com.twitter.android.analytics.TweetAnalyticsWebViewActivity", "com.twitter.android.ads.AdsInfoWebViewActivity", "com.twitter.android.ads.AdsCompanionWebViewActivity", "com.twitter.android.ads.AdsPromoteModeWebViewActivity", "com.twitter.android.settings.UserTwitterDataWebViewActivity", "com.twitter.android.browser.BrowserActivity", "com.twitter.composer.draft.DraftsActivity", "com.twitter.android.AccountsDialogActivity", "com.twitter.android.RemoveAccountActivity", "com.twitter.android.RemoveAccountDialogActivity", "com.twitter.android.settings.DeactivateAccountActivity", "com.twitter.android.settings.ConfirmDeactivateAccountActivity", "com.twitter.android.settings.AccountDeactivatedActivity", "com.twitter.android.ReportFlowWebViewActivity", "com.twitter.android.BouncerWebViewActivity", "com.twitter.app.deeplink.UrlInterpreterActivity", "com.twitter.android.trends.TrendsLocationsActivity", "com.twitter.android.settings.country.CountryListActivity", "com.twitter.android.TwoFactorAuthSettingsActivity", "com.twitter.android.SecuritySettingsActivity", "com.twitter.android.settings.DiscoverabilityActivity", "com.twitter.android.settings.RemoveContactsActivity", "com.twitter.android.settings.TweetSettingsActivity", "com.twitter.android.MediaTagActivity", "com.twitter.android.AltTextActivity", "com.twitter.android.AVMediaPlayerActivity", "com.twitter.android.broadcast.fullscreen.BroadcastFullscreenActivity", "com.twitter.android.broadcast.LexLocationPromptActivity", "com.twitter.android.broadcast.deeplink.BroadcastDeeplinkActivity", "com.twitter.periscope.broadcaster.PeriscopePermissionHelperActivity", "com.twitter.periscope.broadcaster.PeriscopeBroadcasterActivity", "com.twitter.periscope.account.PeriscopeBanningActivity", "com.twitter.android.av.audio.AudioCardViewerActivity", "com.twitter.android.av.revenue.VideoConversationCardCanvasActivity", "com.twitter.android.av.revenue.VideoDirectMessageCardCanvasActivity", "com.twitter.android.GalleryActivity", "com.twitter.android.fullscreenmediaplayer.FullscreenMediaPlayerActivity", "com.twitter.android.av.monetization.MonetizationCategorySelectorActivity", "com.twitter.android.av.monetization.MediaMonetizationSettingsActivity", "com.twitter.android.commerce.view.AuthenticatedWebViewActivity", "com.twitter.android.media.imageeditor.EditImageActivity", "com.twitter.android.media.imageeditor.ProfilePhotoEditImageActivity", "com.twitter.android.media.stickers.timeline.StickerTimelineActivity", "com.twitter.android.trends.TrendsActivity", "com.twitter.android.notificationtimeline.NotificationsDeviceFollowActivity", "com.twitter.android.moments.UserMomentsActivity", "com.twitter.app.dm.DMAddParticipantsActivity", "com.twitter.android.geo.places.PlaceLandingActivity", "com.twitter.android.moments.ui.fullscreen.MomentsFullScreenPagerActivity", "com.twitter.android.moments.urt.URTMomentActivity", "com.twitter.app.users.URTUsersActivity", "com.twitter.app.timeline.GenericTimelineActivity", "com.twitter.app.timeline.GenericCursoringTimelineActivity", "com.twitter.app.chrome.DynamicChromeActivity", "com.twitter.android.notificationtimeline.GenericActivityWebViewActivity", "com.twitter.android.DispatchActivity", "com.twitter.android.StartActivity", "com.twitter.android.DiskCleanupPromptActivity", "com.twitter.android.AuthorizeAppActivity", "com.twitter.app.authorizeapp.AppAuthorizationActivity", "com.twitter.android.SingleSignOnActivity", "com.twitter.android.settings.SettingsActivity", "com.twitter.android.settings.AccountActivity", "com.twitter.android.settings.ContentPreferencesSettingsActivity", "com.twitter.android.settings.PrivacyAndSafetyActivity", "com.twitter.android.settings.PrivacyAndSafetyCompatActivity", "com.twitter.android.settings.PersonalizationSettingsActivity", "com.twitter.android.settings.DisplayAndSoundSettingsActivity", "com.twitter.android.settings.DataSettingsActivity", "com.twitter.android.settings.LocationSettingsActivity", "com.twitter.android.settings.AccessibilityActivity", "com.twitter.android.settings.AboutActivity", "com.twitter.android.settings.ProxySettingsActivity", "com.twitter.android.settings.account.AccountNotificationsActivity", "com.twitter.android.settings.notifications.ConversationNotificationsSettingsActivity", "com.twitter.android.dogfood.BugReporterActivity", "com.twitter.app.safety.mutedkeywords.list.MutedKeywordsListActivity", "com.twitter.app.safety.mutedkeywords.composer.MutedKeywordComposerActivity", "com.twitter.android.settings.notifications.PushNotificationsSettingsActivity", "com.twitter.android.settings.notifications.EmailNotificationsSettingsActivity", "com.twitter.android.settings.notifications.SmsNotificationsSettingsActivity", "com.twitter.app.onboarding.OcfFlowWebActivity", "com.twitter.app.onboarding.permissionstep.LiveSyncPermissionStepActivity", "com.twitter.app.onboarding.contacts.AddressbookContactsStepActivity", "com.twitter.app.onboarding.loading.OcfStartFlowActivity", "com.twitter.app.onboarding.signup.SignUpReviewStepActivity", "com.twitter.app.onboarding.signup.SignUpStepFormActivity", "com.twitter.app.onboarding.dialog.OcfDialogFragmentActivity", "com.twitter.android.navigation.NoOpActivity", "com.twitter.app.onboarding.verification.PhonePinVerificationStepActivity", "com.twitter.app.onboarding.verification.EmailPinVerificationStepActivity", "com.twitter.app.onboarding.password.PasswordEntryStepActivity", "com.twitter.app.onboarding.username.UsernameEntryActivity", "com.twitter.app.onboarding.signup.SignUpSplashActivity", "com.twitter.app.onboarding.signup.PrivacyOptionsActivity", "com.twitter.app.onboarding.username.UsernameSettingActivity", "com.twitter.app.onboarding.username.EditProfileUsernameSettingActivity", "com.twitter.app.onboarding.common.OcfInvisibleSubtaskActivity", "com.twitter.app.onboarding.userrecommendation.UserRecommendationsListActivity", "com.twitter.app.onboarding.interestpicker.InterestPickerActivity", "com.twitter.app.onboarding.common.CtaSubtaskActivity", "com.twitter.app.onboarding.settings.SettingsListSubtaskActivity", "com.twitter.app.onboarding.entertext.EnterTextSubtaskActivity", "com.twitter.app.onboarding.media.SelectAvatarSubtaskActivity", "com.twitter.app.onboarding.media.SelectBannerSubtaskActivity", "com.twitter.android.notificationtimeline.anniversary.AnniversaryLandingActivity", "com.twitter.android.VideoEditorActivity", "com.twitter.android.media.camera.CameraActivity", "com.twitter.android.qrcodes.QRCodeActivity", "com.twitter.android.runtimepermissions.PermissionRequestActivity", "com.twitter.android.addressbook.LiveSyncPermissionRequestActivity", "com.twitter.android.ImageSaverPermissionRequestActivity", "com.twitter.android.revenue.BrowserWithDockedVideoActivity", "com.twitter.android.revenue.BrowserWithDockedImageActivity", "com.twitter.android.settings.TrendsPrefActivity", "com.twitter.app.bookmarks.BookmarkTimelineActivity", "com.twitter.app.users.WhoToFollowUsersTimelineActivity", "com.twitter.app.users.MutedUsersTimelineActivity", "com.twitter.app.timeline.PendingFollowersTimelineActivity", "com.twitter.app.users.FollowingTimelineActivity", "com.twitter.app.users.FollowersTimelineActivity", "com.twitter.app.users.MutualFollowingTimelineActivity", "com.twitter.app.timeline.ReplyContextTimelineActivity", "com.twitter.app.users.ManageListMembersTimelineActivity", "com.twitter.app.timeline.moderation.ViewHiddenTweetsActivity", "com.twitter.camera.consumption.controller.root.CameraFullScreenContainerActivity", "com.twitter.camera.controller.root.CameraActivity", "com.twitter.tweetdetail.TweetDetailActivity2", "com.twitter.onboarding.ocf.common.OcfModalPlaceholderActivity", "tv.periscope.android.library.PeriscopeInterstitialActivity", "tv.periscope.android.ui.broadcast.KickSelfActivity", "tv.periscope.android.ui.profile.ActionRequiredActivity", "com.twitter.notification.dispatch.NotificationDispatchActivity", "com.twitter.notification.dispatch.SettingsDispatchActivity", "com.google.android.gms.auth.api.signin.internal.SignInHubActivity", "com.google.android.gms.common.api.GoogleApiActivity"], "receivers": ["com.twitter.android.client.chrome.ChromeCustomTabsActionReceiver", "com.twitter.android.client.NotifOnClickBroadcastReceiver", "com.twitter.android.client.AppBroadcastReceiver", "com.twitter.android.platform.AppUpdateReceiver", "com.twitter.account.phone.SmsBroadcastReceiver", "com.twitter.analytics.tracking.InstallReferralReceiver", "com.twitter.analytics.tracking.InstallationReferrer$OemIntentReceiver", "com.twitter.app.common.account.AppAccountManager$AccountsChangedReceiver", "com.google.firebase.iid.FirebaseInstanceIdReceiver", "androidx.work.impl.utils.ForceStopRunnable$BroadcastReceiver", "androidx.work.impl.background.systemalarm.ConstraintProxy$BatteryChargingProxy", "androidx.work.impl.background.systemalarm.ConstraintProxy$BatteryNotLowProxy", "androidx.work.impl.background.systemalarm.ConstraintProxy$StorageNotLowProxy", "androidx.work.impl.background.systemalarm.ConstraintProxy$NetworkStateProxy", "androidx.work.impl.background.systemalarm.RescheduleReceiver", "androidx.work.impl.background.systemalarm.ConstraintProxyUpdateReceiver", "com.evernote.android.job.v14.PlatformAlarmReceiver", "com.evernote.android.job.JobBootReceiver"], "providers": ["com.twitter.android.provider.SuggestionsProvider", "androidx.core.content.FileProvider", "com.twitter.database.legacy.gdbh.GlobalDatabaseProvider", "com.twitter.database.legacy.provider.TwitterProvider", "androidx.work.impl.WorkManagerInitializer", "com.google.firebase.provider.FirebaseInitProvider", "androidx.lifecycle.ProcessLifecycleOwnerInitializer", "com.crashlytics.android.CrashlyticsInitProvider"], "services": ["com.twitter.android.client.TweetUploadService", "com.twitter.android.platform.TwitterAuthenticationService", "com.twitter.library.platform.TwitterDataSyncService", "com.twitter.app.dm.DMDirectShareChooser", "com.twitter.android.client.NotificationService", "com.twitter.contacts.upload.ContactsUploadService", "com.twitter.notification.service.firebase.TwitterFirebaseInstanceIdService", "com.twitter.notification.service.firebase.TwitterFirebaseMessagingService", "com.twitter.analytics.service.ScribeService", "com.evernote.android.job.gcm.PlatformGcmService", "com.twitter.launcherbadge.LauncherIconBadgeUpdaterService", "com.twitter.network.usage.service.OverlayService", "com.twitter.media.service.core.MediaService", "com.google.android.gms.auth.api.signin.RevocationBoundService", "com.google.firebase.messaging.FirebaseMessagingService", "com.google.firebase.components.ComponentDiscoveryService", "com.google.firebase.iid.FirebaseInstanceIdService", "androidx.work.impl.background.systemalarm.SystemAlarmService", "androidx.work.impl.background.systemjob.SystemJobService", "com.evernote.android.job.v21.PlatformJobService", "com.evernote.android.job.v14.PlatformAlarmService", "com.evernote.android.job.v14.PlatformAlarmServiceExact", "com.evernote.android.job.JobRescheduleService"], "libraries": ["org.apache.http.legacy"], "target_sdk": "28", "max_sdk": "", "min_sdk": "19", "version_name": "7.93.4-release.05", "version_code": "17934005", "permissions": {"com.twitter.android.permission.RESTRICTED": {"status": "dangerous", "info": "Unknown permission from android reference", "description": "Unknown permission from android reference"}, "android.permission.INTERNET": {"status": "dangerous", "info": "full Internet access", "description": "Allows an application to create network sockets."}, "android.permission.ACCESS_NETWORK_STATE": {"status": "normal", "info": "view network status", "description": "Allows an application to view the status of all networks."}, "android.permission.VIBRATE": {"status": "normal", "info": "control vibrator", "description": "Allows the application to control the vibrator."}, "android.permission.READ_PROFILE": {"status": "dangerous", "info": "read the user's personal profile data", "description": "Allows an application to read the user's personal profile data."}, "android.permission.READ_CONTACTS": {"status": "dangerous", "info": "read contact data", "description": "Allows an application to read all of the contact (address) data stored on your phone. Malicious applications can use this to send your data to other people."}, "android.permission.GET_ACCOUNTS": {"status": "normal", "info": "discover known accounts", "description": "Allows an application to access the list of accounts known by the phone."}, "android.permission.MANAGE_ACCOUNTS": {"status": "dangerous", "info": "manage the accounts list", "description": "Allows an application to perform operations like adding and removing accounts and deleting their password."}, "android.permission.AUTHENTICATE_ACCOUNTS": {"status": "dangerous", "info": "act as an account authenticator", "description": "Allows an application to use the account authenticator capabilities of the Account Manager, including creating accounts as well as obtaining and setting their passwords."}, "android.permission.READ_SYNC_SETTINGS": {"status": "normal", "info": "read sync settings", "description": "Allows an application to read the sync settings, such as whether sync is enabled for Contacts."}, "android.permission.WRITE_SYNC_SETTINGS": {"status": "dangerous", "info": "write sync settings", "description": "Allows an application to modify the sync settings, such as whether sync is enabled for Contacts."}, "android.permission.ACCESS_FINE_LOCATION": {"status": "dangerous", "info": "fine (GPS) location", "description": "Access fine location sources, such as the Global Positioning System on the phone, where available. Malicious applications can use this to determine where you are and may consume additional battery power."}, "android.permission.USE_CREDENTIALS": {"status": "dangerous", "info": "use the authentication credentials of an account", "description": "Allows an application to request authentication tokens."}, "android.permission.SYSTEM_ALERT_WINDOW": {"status": "dangerous", "info": "display system-level alerts", "description": "Allows an application to show system-alert windows. Malicious applications can take over the entire screen of the phone."}, "android.permission.WAKE_LOCK": {"status": "dangerous", "info": "prevent phone from sleeping", "description": "Allows an application to prevent the phone from going to sleep."}, "android.permission.WRITE_EXTERNAL_STORAGE": {"status": "dangerous", "info": "read/modify/delete SD card contents", "description": "Allows an application to write to the SD card."}, "com.twitter.android.permission.READ_DATA": {"status": "dangerous", "info": "Unknown permission from android reference", "description": "Unknown permission from android reference"}, "com.google.android.providers.gsf.permission.READ_GSERVICES": {"status": "dangerous", "info": "Unknown permission from android reference", "description": "Unknown permission from android reference"}, "com.android.launcher.permission.INSTALL_SHORTCUT": {"status": "normal", "info": "", "description": "Allows an application to install a shortcut in Launcher."}, "android.permission.READ_PHONE_STATE": {"status": "dangerous", "info": "read phone state and identity", "description": "Allows the application to access the phone features of the device. An application with this permission can determine the phone number and serial number of this phone, whether a call is active, the number that call is connected to and so on."}, "android.permission.CAMERA": {"status": "dangerous", "info": "take pictures and videos", "description": "Allows application to take pictures and videos with the camera. This allows the application to collect images that the camera is seeing at any time."}, "android.permission.RECORD_AUDIO": {"status": "dangerous", "info": "record audio", "description": "Allows application to access the audio record path."}, "android.permission.ACCESS_COARSE_LOCATION": {"status": "dangerous", "info": "coarse (network-based) location", "description": "Access coarse location sources, such as the mobile network database, to determine an approximate phone location, where available. Malicious applications can use this to determine approximately where you are."}, "com.huawei.android.launcher.permission.READ_SETTINGS": {"status": "dangerous", "info": "Unknown permission from android reference", "description": "Unknown permission from android reference"}, "com.huawei.android.launcher.permission.WRITE_SETTINGS": {"status": "dangerous", "info": "modify global system settings", "description": "Allows an application to modify the system's settings data. Malicious applications can corrupt your system's configuration."}, "com.huawei.android.launcher.permission.CHANGE_BADGE": {"status": "dangerous", "info": "Unknown permission from android reference", "description": "Unknown permission from android reference"}, "com.sonyericsson.home.permission.BROADCAST_BADGE": {"status": "dangerous", "info": "Unknown permission from android reference", "description": "Unknown permission from android reference"}, "com.sonymobile.home.permission.PROVIDER_INSERT_BADGE": {"status": "dangerous", "info": "Unknown permission from android reference", "description": "Unknown permission from android reference"}, "com.sec.android.provider.badge.permission.READ": {"status": "dangerous", "info": "Unknown permission from android reference", "description": "Unknown permission from android reference"}, "com.sec.android.provider.badge.permission.WRITE": {"status": "dangerous", "info": "Unknown permission from android reference", "description": "Unknown permission from android reference"}, "com.oppo.launcher.permission.READ_SETTINGS": {"status": "dangerous", "info": "Unknown permission from android reference", "description": "Unknown permission from android reference"}, "com.oppo.launcher.permission.WRITE_SETTINGS": {"status": "dangerous", "info": "modify global system settings", "description": "Allows an application to modify the system's settings data. Malicious applications can corrupt your system's configuration."}, "com.htc.launcher.permission.READ_SETTINGS": {"status": "dangerous", "info": "Unknown permission from android reference", "description": "Unknown permission from android reference"}, "com.htc.launcher.permission.UPDATE_SHORTCUT": {"status": "dangerous", "info": "Unknown permission from android reference", "description": "Unknown permission from android reference"}, "com.anddoes.launcher.permission.UPDATE_COUNT": {"status": "dangerous", "info": "Unknown permission from android reference", "description": "Unknown permission from android reference"}, "android.permission.ACCESS_WIFI_STATE": {"status": "normal", "info": "view Wi-Fi status", "description": "Allows an application to view the information about the status of Wi-Fi."}, "com.google.android.c2dm.permission.RECEIVE": {"status": "signature", "info": "C2DM permissions", "description": "Permission for cloud to device messaging."}, "android.permission.RECEIVE_BOOT_COMPLETED": {"status": "normal", "info": "automatically start at boot", "description": "Allows an application to start itself as soon as the system has finished booting. This can make it take longer to start the phone and allow the application to slow down the overall phone by always running."}, "android.permission.READ_EXTERNAL_STORAGE": {"status": "dangerous", "info": "read SD card contents", "description": "Allows an application to read from SD Card."}, "com.google.android.finsky.permission.BIND_GET_INSTALL_REFERRER_SERVICE": {"status": "dangerous", "info": "Unknown permission from android reference", "description": "Unknown permission from android reference"}}, "certificate_analysis": {"certificate_info": "APK is signed\nv1 signature: True\nv2 signature: True\nv3 signature: False\nFound 1 unique certificates\nSubject: C=US, ST=CA, L=San Francisco, O=Twitter, Inc., OU=Mobile, CN=Leland Rechis\nSignature Algorithm: rsassa_pkcs1v15\nValid From: 2010-04-27 23:01:34+00:00\nValid To: 2048-08-25 23:01:34+00:00\nIssuer: C=US, ST=CA, L=San Francisco, O=Twitter, Inc., OU=Mobile, CN=Leland Rechis\nSerial Number: 0x4bd76cce\nHash Algorithm: sha1\nmd5: 69ee076cc84f4d94802d61907b07525f\nsha1: 40f3166bb567d3144bca7da466bb948b782270ea\nsha256: 0fd9a0cfb07b65950997b4eaebdc53931392391aa406538a3b04073bc2ce2fe9\nsha512: bb403e3bb22fba89239ea99fd5c89a8328b0931aac2d2ad703d673c886f8c86115bb9b4f45f8496e7f111071a60c052450219fef54eac1473049fc0539b46cb0\nPublicKey Algorithm: rsa\nBit Size: 1024\nFingerprint: 8d0c8a8fec5ae65ac901233e20011d31d296a1481f765bd5a41009c3aaef4f72", "certificate_status": "warning", "description": "The app is signed with SHA1withRSA. SHA1 hash algorithm is known to have collision issues.The manifest indicates SHA256withRSA is in use. Please verify this manually."}, "manifest_analysis": [{"title": "Clear text traffic is Enabled For App<br>[android:usesCleartextTraffic=true]", "stat": "high", "desc": "The app intends to use cleartext network traffic, such as cleartext HTTP, FTP stacks, DownloadManager, and MediaPlayer. The default value for apps that target API level 27 or lower is \"true\". Apps that target API level 28 or higher default to \"false\". The key reason for avoiding cleartext traffic is the lack of confidentiality, authenticity, and protections against tampering; a network attacker can eavesdrop on transmitted data and also modify it without being detected.", "name": "Clear text traffic is Enabled For App [android:usesCleartextTraffic=true]", "component": []}, {"title": "Application Data can be Backed up<br>[android:allowBackup] flag is missing.", "stat": "medium", "desc": "The flag [android:allowBackup] should be set to false. By default it is set to true and allows anyone to backup your application data via adb. It allows users who have enabled USB debugging to copy application data off of the device.", "name": "Application Data can be Backed up [android:allowBackup] flag is missing.", "component": []}, {"title": "<strong>Activity</strong> (com.twitter.android.search.SearchActivity) is not Protected.<br>An intent-filter exists.", "stat": "high", "desc": "An Activity is found to be shared with other apps on the device therefore leaving it accessible to any other application on the device. The presence of intent-filter indicates that the Activity is explicitly exported.", "name": "is not Protected.An intent-filter exists.", "component": ["Activity", "com.twitter.android.search.SearchActivity"]}, {"title": "<strong>Activity</strong> (com.twitter.composer.ComposerActivity) is not Protected.<br>An intent-filter exists.", "stat": "high", "desc": "An Activity is found to be shared with other apps on the device therefore leaving it accessible to any other application on the device. The presence of intent-filter indicates that the Activity is explicitly exported.", "name": "is not Protected.An intent-filter exists.", "component": ["Activity", "com.twitter.composer.ComposerActivity"]}, {"title": "<strong>Activity</strong> (com.twitter.app.dm.DMActivity) is not Protected.<br>An intent-filter exists.", "stat": "high", "desc": "An Activity is found to be shared with other apps on the device therefore leaving it accessible to any other application on the device. The presence of intent-filter indicates that the Activity is explicitly exported.", "name": "is not Protected.An intent-filter exists.", "component": ["Activity", "com.twitter.app.dm.DMActivity"]}, {"title": "<strong>Activity</strong> (com.twitter.android.ProfileActivity) is not Protected.<br>An intent-filter exists.", "stat": "high", "desc": "An Activity is found to be shared with other apps on the device therefore leaving it accessible to any other application on the device. The presence of intent-filter indicates that the Activity is explicitly exported.", "name": "is not Protected.An intent-filter exists.", "component": ["Activity", "com.twitter.android.ProfileActivity"]}, {"title": "Launch Mode of Activity (com.twitter.android.BouncerWebViewActivity) is not standard.", "stat": "high", "desc": "An Activity should not be having the launch mode attribute set to \"singleTask/singleInstance\" as it becomes root Activity and it is possible for other applications to read the contents of the calling Intent. So it is required to use the \"standard\" launch mode attribute when sensitive information is included in an Intent.", "name": "Launch Mode of Activity is not standard.", "component": ["com.twitter.android.BouncerWebViewActivity"]}, {"title": "Launch Mode of Activity (com.twitter.app.deeplink.UrlInterpreterActivity) is not standard.", "stat": "high", "desc": "An Activity should not be having the launch mode attribute set to \"singleTask/singleInstance\" as it becomes root Activity and it is possible for other applications to read the contents of the calling Intent. So it is required to use the \"standard\" launch mode attribute when sensitive information is included in an Intent.", "name": "Launch Mode of Activity is not standard.", "component": ["com.twitter.app.deeplink.UrlInterpreterActivity"]}, {"title": "<strong>Activity</strong> (com.twitter.app.deeplink.UrlInterpreterActivity) is not Protected.<br>An intent-filter exists.", "stat": "high", "desc": "An Activity is found to be shared with other apps on the device therefore leaving it accessible to any other application on the device. The presence of intent-filter indicates that the Activity is explicitly exported.", "name": "is not Protected.An intent-filter exists.", "component": ["Activity", "com.twitter.app.deeplink.UrlInterpreterActivity"]}, {"title": "Launch Mode of Activity (com.twitter.periscope.broadcaster.PeriscopePermissionHelperActivity) is not standard.", "stat": "high", "desc": "An Activity should not be having the launch mode attribute set to \"singleTask/singleInstance\" as it becomes root Activity and it is possible for other applications to read the contents of the calling Intent. So it is required to use the \"standard\" launch mode attribute when sensitive information is included in an Intent.", "name": "Launch Mode of Activity is not standard.", "component": ["com.twitter.periscope.broadcaster.PeriscopePermissionHelperActivity"]}, {"title": "Launch Mode of Activity (com.twitter.periscope.broadcaster.PeriscopeBroadcasterActivity) is not standard.", "stat": "high", "desc": "An Activity should not be having the launch mode attribute set to \"singleTask/singleInstance\" as it becomes root Activity and it is possible for other applications to read the contents of the calling Intent. So it is required to use the \"standard\" launch mode attribute when sensitive information is included in an Intent.", "name": "Launch Mode of Activity is not standard.", "component": ["com.twitter.periscope.broadcaster.PeriscopeBroadcasterActivity"]}, {"title": "<strong>Activity</strong> (com.twitter.android.AuthorizeAppActivity) is not Protected. <br>[android:exported=true]", "stat": "high", "desc": "An Activity is found to be shared with other apps on the device therefore leaving it accessible to any other application on the device.", "name": "is not Protected. [android:exported=true]", "component": ["Activity", "com.twitter.android.AuthorizeAppActivity"]}, {"title": "<strong>Activity</strong> (com.twitter.android.SingleSignOnActivity) is not Protected. <br>[android:exported=true]", "stat": "high", "desc": "An Activity is found to be shared with other apps on the device therefore leaving it accessible to any other application on the device.", "name": "is not Protected. [android:exported=true]", "component": ["Activity", "com.twitter.android.SingleSignOnActivity"]}, {"title": "Launch Mode of Activity (com.twitter.android.dogfood.BugReporterActivity) is not standard.", "stat": "high", "desc": "An Activity should not be having the launch mode attribute set to \"singleTask/singleInstance\" as it becomes root Activity and it is possible for other applications to read the contents of the calling Intent. So it is required to use the \"standard\" launch mode attribute when sensitive information is included in an Intent.", "name": "Launch Mode of Activity is not standard.", "component": ["com.twitter.android.dogfood.BugReporterActivity"]}, {"title": "Launch Mode of Activity (com.twitter.app.onboarding.verification.EmailPinVerificationStepActivity) is not standard.", "stat": "high", "desc": "An Activity should not be having the launch mode attribute set to \"singleTask/singleInstance\" as it becomes root Activity and it is possible for other applications to read the contents of the calling Intent. So it is required to use the \"standard\" launch mode attribute when sensitive information is included in an Intent.", "name": "Launch Mode of Activity is not standard.", "component": ["com.twitter.app.onboarding.verification.EmailPinVerificationStepActivity"]}, {"title": "<strong>Broadcast Receiver</strong> (com.twitter.android.client.AppBroadcastReceiver) is Protected by a permission.</br><strong>Permission: </strong>com.twitter.android.permission.RESTRICTED</br><strong>protectionLevel: </strong>signature<br>[android:exported=true]", "stat": "info", "desc": "A Broadcast Receiver is found to be exported, but is protected by permission.", "name": "is Protected by a permission.[android:exported=true]", "component": ["Broadcast Receiver", "com.twitter.android.client.AppBroadcastReceiver", "<strong>Permission: </strong>com.twitter.android.permission.RESTRICTED</br><strong>protectionLevel: </strong>signature"]}, {"title": "<strong>Broadcast Receiver</strong> (com.twitter.android.platform.AppUpdateReceiver) is not Protected.<br>An intent-filter exists.", "stat": "high", "desc": "A Broadcast Receiver is found to be shared with other apps on the device therefore leaving it accessible to any other application on the device. The presence of intent-filter indicates that the Broadcast Receiver is explicitly exported.", "name": "is not Protected.An intent-filter exists.", "component": ["Broadcast Receiver", "com.twitter.android.platform.AppUpdateReceiver"]}, {"title": "<strong>Broadcast Receiver</strong> (com.twitter.account.phone.SmsBroadcastReceiver) is not Protected. <br>[android:exported=true]", "stat": "high", "desc": "A Broadcast Receiver is found to be shared with other apps on the device therefore leaving it accessible to any other application on the device.", "name": "is not Protected. [android:exported=true]", "component": ["Broadcast Receiver", "com.twitter.account.phone.SmsBroadcastReceiver"]}, {"title": "<strong>Service</strong> (com.twitter.notification.service.firebase.TwitterFirebaseMessagingService) is not Protected.<br>An intent-filter exists.", "stat": "high", "desc": "A Service is found to be shared with other apps on the device therefore leaving it accessible to any other application on the device. The presence of intent-filter indicates that the Service is explicitly exported.", "name": "is not Protected.An intent-filter exists.", "component": ["Service", "com.twitter.notification.service.firebase.TwitterFirebaseMessagingService"]}, {"title": "<strong>Broadcast Receiver</strong> (com.twitter.analytics.tracking.InstallReferralReceiver) is not Protected. <br>[android:exported=true]", "stat": "high", "desc": "A Broadcast Receiver is found to be shared with other apps on the device therefore leaving it accessible to any other application on the device.", "name": "is not Protected. [android:exported=true]", "component": ["Broadcast Receiver", "com.twitter.analytics.tracking.InstallReferralReceiver"]}, {"title": "<strong>Broadcast Receiver</strong> (com.twitter.analytics.tracking.InstallationReferrer$OemIntentReceiver) is not Protected. <br>[android:exported=true]", "stat": "high", "desc": "A Broadcast Receiver is found to be shared with other apps on the device therefore leaving it accessible to any other application on the device.", "name": "is not Protected. [android:exported=true]", "component": ["Broadcast Receiver", "com.twitter.analytics.tracking.InstallationReferrer$OemIntentReceiver"]}, {"title": "<strong>Service</strong> (com.evernote.android.job.gcm.PlatformGcmService) is Protected by a permission, but the protection level of the permission should be checked.</br><strong>Permission: </strong>com.google.android.gms.permission.BIND_NETWORK_TASK_SERVICE <br>[android:exported=true]", "stat": "high", "desc": "A Service is found to be shared with other apps on the device therefore leaving it accessible to any other application on the device. It is protected by a permission which is not defined in the analysed application. As a result, the protection level of the permission should be checked where it is defined. If it is set to normal or dangerous, a malicious application can request and obtain the permission and interact with the component. If it is set to signature, only applications signed with the same certificate can obtain the permission.", "name": "is Protected by a permission, but the protection level of the permission should be checked.[android:exported=true]", "component": ["Service", "com.evernote.android.job.gcm.PlatformGcmService", "<strong>Permission: </strong>com.google.android.gms.permission.BIND_NETWORK_TASK_SERVICE"]}, {"title": "<strong>Broadcast Receiver</strong> (com.twitter.app.common.account.AppAccountManager$AccountsChangedReceiver) is not Protected.<br>An intent-filter exists.", "stat": "high", "desc": "A Broadcast Receiver is found to be shared with other apps on the device therefore leaving it accessible to any other application on the device. The presence of intent-filter indicates that the Broadcast Receiver is explicitly exported.", "name": "is not Protected.An intent-filter exists.", "component": ["Broadcast Receiver", "com.twitter.app.common.account.AppAccountManager$AccountsChangedReceiver"]}, {"title": "<strong>Service</strong> (com.google.android.gms.auth.api.signin.RevocationBoundService) is Protected by a permission, but the protection level of the permission should be checked.</br><strong>Permission: </strong>com.google.android.gms.auth.api.signin.permission.REVOCATION_NOTIFICATION <br>[android:exported=true]", "stat": "high", "desc": "A Service is found to be shared with other apps on the device therefore leaving it accessible to any other application on the device. It is protected by a permission which is not defined in the analysed application. As a result, the protection level of the permission should be checked where it is defined. If it is set to normal or dangerous, a malicious application can request and obtain the permission and interact with the component. If it is set to signature, only applications signed with the same certificate can obtain the permission.", "name": "is Protected by a permission, but the protection level of the permission should be checked.[android:exported=true]", "component": ["Service", "com.google.android.gms.auth.api.signin.RevocationBoundService", "<strong>Permission: </strong>com.google.android.gms.auth.api.signin.permission.REVOCATION_NOTIFICATION"]}, {"title": "<strong>Service</strong> (com.google.firebase.messaging.FirebaseMessagingService) is not Protected. <br>[android:exported=true]", "stat": "high", "desc": "A Service is found to be shared with other apps on the device therefore leaving it accessible to any other application on the device.", "name": "is not Protected. [android:exported=true]", "component": ["Service", "com.google.firebase.messaging.FirebaseMessagingService"]}, {"title": "<strong>Broadcast Receiver</strong> (com.google.firebase.iid.FirebaseInstanceIdReceiver) is Protected by a permission, but the protection level of the permission should be checked.</br><strong>Permission: </strong>com.google.android.c2dm.permission.SEND <br>[android:exported=true]", "stat": "high", "desc": "A Broadcast Receiver is found to be shared with other apps on the device therefore leaving it accessible to any other application on the device. It is protected by a permission which is not defined in the analysed application. As a result, the protection level of the permission should be checked where it is defined. If it is set to normal or dangerous, a malicious application can request and obtain the permission and interact with the component. If it is set to signature, only applications signed with the same certificate can obtain the permission.", "name": "is Protected by a permission, but the protection level of the permission should be checked.[android:exported=true]", "component": ["Broadcast Receiver", "com.google.firebase.iid.FirebaseInstanceIdReceiver", "<strong>Permission: </strong>com.google.android.c2dm.permission.SEND"]}, {"title": "<strong>Service</strong> (com.google.firebase.iid.FirebaseInstanceIdService) is not Protected. <br>[android:exported=true]", "stat": "high", "desc": "A Service is found to be shared with other apps on the device therefore leaving it accessible to any other application on the device.", "name": "is not Protected. [android:exported=true]", "component": ["Service", "com.google.firebase.iid.FirebaseInstanceIdService"]}, {"title": "<strong>Service</strong> (androidx.work.impl.background.systemjob.SystemJobService) is Protected by a permission, but the protection level of the permission should be checked.</br><strong>Permission: </strong>android.permission.BIND_JOB_SERVICE <br>[android:exported=true]", "stat": "high", "desc": "A Service is found to be shared with other apps on the device therefore leaving it accessible to any other application on the device. It is protected by a permission which is not defined in the analysed application. As a result, the protection level of the permission should be checked where it is defined. If it is set to normal or dangerous, a malicious application can request and obtain the permission and interact with the component. If it is set to signature, only applications signed with the same certificate can obtain the permission.", "name": "is Protected by a permission, but the protection level of the permission should be checked.[android:exported=true]", "component": ["Service", "androidx.work.impl.background.systemjob.SystemJobService", "<strong>Permission: </strong>android.permission.BIND_JOB_SERVICE"]}], "binary_analysis": [], "file_analysis": [{"finding": "Certificate/Key files hardcoded inside the app.", "files": ["res/raw/cacerts"]}], "code_analysis": {"App creates temp file. Sensitive information should never be written into a temp file.": {"path": ["com/github/luben/zstd/util/Native.java", "defpackage/fw.java", "defpackage/pm.java", "defpackage/ngp.java", "defpackage/kyy.java"], "level": "high", "cvss": 5.5, "cwe": "CWE-276", "owasp": "M2: Insecure Data Storage"}, "The App logs information. Sensitive information should never be logged.": {"path": ["com/github/mikephil/charting/charts/b.java", "com/github/mikephil/charting/charts/c.java", "com/github/mikephil/charting/charts/d.java", "com/github/mikephil/charting/charts/a.java", "com/airbnb/deeplinkdispatch/BaseDeepLinkDelegate.java", "com/caverock/androidsvg/f.java", "com/caverock/androidsvg/a.java", "com/caverock/androidsvg/h.java", "defpackage/ca.java", "defpackage/ja.java", "defpackage/kjn.java", "defpackage/cd.java", "defpackage/ch.java", "defpackage/npn.java", "defpackage/asw.java", "defpackage/il.java", "defpackage/di.java", "defpackage/aqg.java", "defpackage/iq.java", "defpackage/ik.java", "defpackage/sr.java", "defpackage/arg.java", "defpackage/fw.java", "defpackage/mou.java", "defpackage/ge.java", "defpackage/gg.java", "defpackage/$$Lambda$gtz$Msm9p0QMnZviK4LpDP7HqgCSafI.java", "defpackage/arj.java", "defpackage/gq.java", "defpackage/$$Lambda$gtz$ZsLgg4nSQ3eU8Ls38o7Su_9HTvQ.java", "defpackage/asx.java", "defpackage/abf.java", "defpackage/s.java", "defpackage/ip.java", "defpackage/hp.java", "defpackage/bw.java", "defpackage/aqi.java", "defpackage/asi.java", "defpackage/jg.java", "defpackage/bsh.java", "defpackage/kss.java", "defpackage/fm.java", "defpackage/nah.java", "defpackage/cse.java", "defpackage/dy.java", "defpackage/$$Lambda$gub$QL_xEgIyziB3dgRDxFCKvSUmI.java", "defpackage/acg.java", "defpackage/cr.java", "defpackage/leu.java", "defpackage/aki.java", "defpackage/lpn.java", "defpackage/is.java", "defpackage/aob.java", "defpackage/ea.java", "defpackage/fh.java", "defpackage/cx.java", "defpackage/zz.java", "defpackage/fu.java", "defpackage/fp.java", "defpackage/aag.java", "defpackage/$$Lambda$gud$xdSmdFuV40pGH7ySspIu1KZOtoo.java", "defpackage/fv.java", "defpackage/nag.java", "defpackage/ir.java", "defpackage/$$Lambda$gub$bqtS2Ph9WeoPIF3cABgG8Zt1U4.java", "defpackage/ana.java", "defpackage/asq.java", "defpackage/mx.java", "defpackage/hm.java", "defpackage/g.java", "defpackage/ft.java", "defpackage/bs.java", "defpackage/apz.java", "defpackage/ngp.java", "defpackage/lc.java", "defpackage/akj.java", "defpackage/asl.java", "defpackage/naf.java", "defpackage/la.java", "defpackage/de.java", "defpackage/csg.java", "defpackage/ce.java", "defpackage/asm.java", "defpackage/ew.java", "defpackage/dk.java", "de/greenrobot/event/b.java", "de/greenrobot/event/c.java", "de/greenrobot/event/k.java"], "level": "info", "cvss": 7.5, "cwe": "CWE-532", "owasp": ""}, "This App uses Java Hash Code. It's a weak hash function and should never be used in Secure Crypto Implementation.": {"path": ["com/fasterxml/jackson/core/JsonLocation.java", "com/fasterxml/jackson/core/Version.java", "com/fasterxml/jackson/core/Base64Variant.java", "com/fasterxml/jackson/core/io/SerializedString.java", "com/fasterxml/jackson/databind/PropertyName.java", "com/fasterxml/jackson/databind/JavaType.java", "com/fasterxml/jackson/databind/jsonschema/JsonSchema.java", "com/fasterxml/jackson/databind/type/ReferenceType.java", "com/fasterxml/jackson/databind/type/TypeBindings.java", "com/fasterxml/jackson/databind/type/ClassKey.java", "com/fasterxml/jackson/databind/type/ArrayType.java", "com/fasterxml/jackson/databind/type/MapLikeType.java", "com/fasterxml/jackson/databind/type/CollectionLikeType.java", "com/fasterxml/jackson/databind/ser/impl/ReadOnlyClassToSerializerMap.java", "com/fasterxml/jackson/databind/node/BigIntegerNode.java", "com/fasterxml/jackson/databind/node/ObjectNode.java", "com/fasterxml/jackson/databind/node/POJONode.java", "com/fasterxml/jackson/databind/node/TextNode.java", "com/fasterxml/jackson/databind/node/ArrayNode.java", "com/fasterxml/jackson/databind/node/DecimalNode.java", "com/fasterxml/jackson/databind/introspect/AnnotatedClass.java", "com/fasterxml/jackson/databind/introspect/AnnotatedField.java", "com/fasterxml/jackson/databind/introspect/AnnotatedMethod.java", "com/fasterxml/jackson/databind/introspect/AnnotatedConstructor.java", "com/fasterxml/jackson/databind/introspect/AnnotatedParameter.java", "com/fasterxml/jackson/databind/introspect/VirtualAnnotatedMember.java", "com/fasterxml/jackson/databind/introspect/MemberKey.java", "com/fasterxml/jackson/databind/util/CompactStringObjectMap.java", "com/fasterxml/jackson/databind/util/RawValue.java", "com/fasterxml/jackson/databind/util/TypeKey.java", "com/fasterxml/jackson/databind/deser/impl/CreatorCollector.java", "com/fasterxml/jackson/databind/deser/impl/BeanPropertyMap.java", "com/fasterxml/jackson/databind/jsontype/NamedType.java", "com/fasterxml/jackson/annotation/JsonFormat.java", "com/fasterxml/jackson/annotation/ObjectIdGenerator.java", "com/fasterxml/jackson/annotation/JsonInclude.java", "com/evernote/android/job/c.java", "com/evernote/android/job/k.java", "com/airbnb/deeplinkdispatch/DeepLinkResult.java", "com/airbnb/deeplinkdispatch/DeepLinkUri.java", "com/caverock/androidsvg/f.java", "com/caverock/androidsvg/a.java", "com/caverock/androidsvg/h.java", "retrofit2/Utils.java", "defpackage/ind.java", "defpackage/haw.java", "defpackage/bcr.java", "defpackage/tu.java", "defpackage/agg.java", "defpackage/aik.java", "defpackage/chk.java", "defpackage/iqp.java", "defpackage/avt.java", "defpackage/myt.java", "defpackage/fwv.java", "defpackage/fvx.java", "defpackage/rj.java", "defpackage/dxp.java", "defpackage/ilj.java", "defpackage/lms.java", "defpackage/iow.java", "defpackage/llq.java", "defpackage/ikj.java", "defpackage/ilt.java", "defpackage/inh.java", "defpackage/iqr.java", "defpackage/gwl.java", "defpackage/agt.java", "defpackage/fnz.java", "defpackage/fwt.java", "defpackage/jv.java", "defpackage/lmz.java", "defpackage/jaz.java", "defpackage/fwc.java", "defpackage/fvw.java", "defpackage/lor.java", "defpackage/gn.java", "defpackage/iom.java", "defpackage/iiz.java", "defpackage/fwq.java", "defpackage/gkn.java", "defpackage/pb.java", "defpackage/lle.java", "defpackage/iv.java", "defpackage/dgg.java", "defpackage/mjy.java", "defpackage/giv.java", "defpackage/aht.java", "defpackage/bvi.java", "defpackage/nbl.java", "defpackage/jil.java", "defpackage/heu.java", "defpackage/lmd.java", "defpackage/mjm.java", "defpackage/fvu.java", "defpackage/kso.java", "defpackage/hby.java", "defpackage/gjk.java", "defpackage/cyf.java", "defpackage/lml.java", "defpackage/nmt.java", "defpackage/nff.java", "defpackage/mc.java", "defpackage/inf.java", "defpackage/fnl.java", "defpackage/agu.java", "defpackage/kls.java", "defpackage/ifw.java", "defpackage/hap.java", "defpackage/arg.java", "defpackage/ke.java", "defpackage/gxl.java", "defpackage/myv.java", "defpackage/lmm.java", "defpackage/lly.java", "defpackage/fvy.java", "defpackage/lmp.java", "defpackage/ied.java", "defpackage/ikf.java", "defpackage/mos.java", "defpackage/aeg.java", "defpackage/agl.java", "defpackage/jql.java", "defpackage/iiy.java", "defpackage/lrw.java", "defpackage/ioc.java", "defpackage/mvq.java", "defpackage/fwl.java", "defpackage/ei.java", "defpackage/iox.java", "defpackage/ief.java", "defpackage/jhi.java", "defpackage/ila.java", "defpackage/aj.java", "defpackage/crl.java", "defpackage/jee.java", "defpackage/iw.java", "defpackage/eh.java", "defpackage/llh.java", "defpackage/aoe.java", "defpackage/fwg.java", "defpackage/cde.java", "defpackage/gqd.java", "defpackage/nrz.java", "defpackage/isj.java", "defpackage/mtp.java", "defpackage/cok.java", "defpackage/idz.java", "defpackage/loh.java", "defpackage/bum.java", "defpackage/mjt.java", "defpackage/nrw.java", "defpackage/ju.java", "defpackage/iqq.java", "defpackage/lx.java", "defpackage/nej.java", "defpackage/fwe.java", "defpackage/ncl.java", "defpackage/ieb.java", "defpackage/kht.java", "defpackage/llu.java", "defpackage/dwt.java", "defpackage/cmo.java", "defpackage/llr.java", "defpackage/mwf.java", "defpackage/agc.java", "defpackage/avh.java", "defpackage/clz.java", "defpackage/llm.java", "defpackage/agm.java", "defpackage/ita.java", "defpackage/mzs.java", "defpackage/iek.java", "defpackage/mxl.java", "defpackage/llw.java", "defpackage/gao.java", "defpackage/irv.java", "defpackage/ivy.java", "defpackage/jbf.java", "defpackage/neh.java", "defpackage/hfa.java", "defpackage/ahx.java", "defpackage/elt.java", "defpackage/an.java", "defpackage/fzc.java", "defpackage/sb.java", "defpackage/ija.java", "defpackage/frg.java", "defpackage/jhe.java", "defpackage/ph.java", "defpackage/lmq.java", "defpackage/ile.java", "defpackage/esw.java", "defpackage/jed.java", "defpackage/iqo.java", "defpackage/llz.java", "defpackage/bvm.java", "defpackage/lmr.java", "defpackage/cou.java", "defpackage/ipb.java", "defpackage/llp.java", "defpackage/nln.java", "defpackage/fwd.java", "defpackage/lmx.java", "defpackage/myz.java", "defpackage/lmw.java", "defpackage/hay.java", "defpackage/dmr.java", "defpackage/cmj.java", "defpackage/agj.java", "defpackage/jcp.java", "defpackage/mtl.java", "defpackage/cph.java", "defpackage/z.java", "defpackage/ef.java", "defpackage/gbg.java", "defpackage/adh.java", "defpackage/euj.java", "defpackage/iog.java", "defpackage/nrx.java", "defpackage/ahv.java", "defpackage/lmn.java", "defpackage/job.java", "defpackage/dxh.java", "defpackage/lld.java", "defpackage/els.java", "defpackage/lgg.java", "defpackage/rk.java", "defpackage/lks.java", "defpackage/nh.java", "defpackage/mxj.java", "defpackage/ios.java", "defpackage/lln.java", "defpackage/lfk.java", "defpackage/ldf.java", "defpackage/lni.java", "defpackage/gdf.java", "defpackage/nmn.java", "defpackage/lmy.java", "defpackage/mgg.java", "defpackage/jbq.java", "defpackage/hak.java", "defpackage/kyx.java", "defpackage/etk.java", "defpackage/hkb.java", "defpackage/cyd.java", "defpackage/ipf.java", "defpackage/nmm.java", "defpackage/fwr.java", "defpackage/ao.java", "defpackage/mzr.java", "defpackage/gqj.java", "defpackage/fwu.java", "defpackage/avs.java", "defpackage/mkb.java", "defpackage/fwk.java", "defpackage/mgi.java", "defpackage/nnm.java", "defpackage/kgp.java", "defpackage/bwa.java", "defpackage/bs.java", "defpackage/aiq.java", "defpackage/fwm.java", "defpackage/mgl.java", "defpackage/pk.java", "defpackage/gjr.java", "defpackage/bzn.java", "defpackage/us.java", "defpackage/hbf.java", "defpackage/jhn.java", "defpackage/jes.java", "defpackage/agq.java", "defpackage/ie.java", "defpackage/kad.java", "defpackage/nbk.java", "defpackage/ado.java", "defpackage/cz.java", "defpackage/pm.java", "defpackage/llf.java", "defpackage/iod.java", "defpackage/nry.java", "defpackage/myo.java", "defpackage/cuf.java", "defpackage/llt.java", "defpackage/ilg.java", "defpackage/dvn.java", "defpackage/arh.java", "defpackage/jaf.java", "defpackage/dvq.java", "defpackage/ags.java", "defpackage/inb.java", "defpackage/nad.java", "defpackage/jzz.java", "defpackage/nbj.java", "defpackage/ilc.java", "defpackage/mpr.java", "defpackage/gwj.java", "defpackage/llx.java", "defpackage/ncg.java", "defpackage/mhw.java", "defpackage/ek.java", "defpackage/dfu.java", "defpackage/kk.java", "defpackage/iou.java", "defpackage/ilu.java", "defpackage/aoq.java", "defpackage/cka.java", "defpackage/cpr.java", "defpackage/gbj.java", "defpackage/lls.java", "defpackage/ini.java", "defpackage/agn.java", "defpackage/ato.java", "defpackage/fwj.java", "defpackage/nmp.java", "defpackage/ajb.java", "defpackage/agi.java", "defpackage/mhg.java", "defpackage/nsh.java", "defpackage/ijd.java", "defpackage/jz.java", "defpackage/jby.java", "defpackage/nfi.java", "defpackage/kid.java", "defpackage/agk.java", "tv/periscope/chatman/api/Reporter.java", "tv/periscope/chatman/model/f.java", "tv/periscope/chatman/model/b.java", "tv/periscope/chatman/model/c.java", "tv/periscope/chatman/model/d.java", "tv/periscope/chatman/model/i.java", "tv/periscope/chatman/model/g.java", "tv/periscope/chatman/model/e.java", "tv/periscope/model/f.java", "tv/periscope/model/C$AutoValue_ProfileImageUrlJSONModel.java", "tv/periscope/model/AutoValue_ProfileImageUrlJSONModel.java", "tv/periscope/model/p.java", "tv/periscope/model/n.java", "tv/periscope/model/s.java", "tv/periscope/model/c.java", "tv/periscope/model/u.java", "tv/periscope/model/q.java", "tv/periscope/model/l.java", "tv/periscope/model/k.java", "tv/periscope/model/t.java", "tv/periscope/model/h.java", "tv/periscope/model/i.java", "tv/periscope/model/o.java", "tv/periscope/model/g.java", "tv/periscope/model/aw.java", "tv/periscope/model/e.java", "tv/periscope/model/aa.java", "tv/periscope/model/j.java", "tv/periscope/model/peopleyoumaylike/AutoValue_PeopleYouMayLikeJSONModel.java", "tv/periscope/model/peopleyoumaylike/C$AutoValue_PeopleYouMayLikeJSONModel.java", "tv/periscope/model/user/b.java", "tv/periscope/model/user/c.java", "tv/periscope/model/user/AutoValue_UserJSONModel.java", "tv/periscope/model/user/a.java", "tv/periscope/model/user/C$AutoValue_UserJSONModel.java", "tv/periscope/model/chat/b.java", "tv/periscope/model/chat/c.java", "tv/periscope/model/chat/d.java", "tv/periscope/model/chat/a.java", "tv/periscope/android/api/PsProfileImageUrl.java", "tv/periscope/android/api/CountryResponse.java", "tv/periscope/android/api/ModeratedCommentInfo.java", "tv/periscope/android/api/ModeratedCommentsResponse.java", "tv/periscope/android/api/FeedItemAdapter.java", "tv/periscope/android/api/PsUser.java", "tv/periscope/android/api/service/suggestedbroadcasts/model/AutoValue_SuggestionReasonJSONModel.java", "tv/periscope/android/api/service/suggestedbroadcasts/model/C$AutoValue_SuggestionReasonJSONModel.java", "tv/periscope/android/api/service/suggestedbroadcasts/model/C$AutoValue_SuggestedBroadcastsJSONModel.java", "tv/periscope/android/api/service/suggestedbroadcasts/model/AutoValue_SuggestedBroadcastsJSONModel.java", "tv/periscope/android/api/service/connectedaccounts/model/C$AutoValue_ConnectedAccountsListJSONModel.java", "tv/periscope/android/api/service/connectedaccounts/model/AutoValue_ConnectedAccountsListJSONModel.java", "tv/periscope/android/api/service/connectedaccounts/model/AutoValue_ConnectedAccountsJSONModel.java", "tv/periscope/android/api/service/connectedaccounts/model/C$AutoValue_ConnectedAccountsJSONModel.java", "tv/periscope/android/api/service/hydra/TurnServerResponse.java", "tv/periscope/android/api/service/hydra/model/guestservice/GuestServiceStreamNegotiationResponse.java", "tv/periscope/android/api/service/hydra/model/guestservice/GuestServiceStreamEjectResponse.java", "tv/periscope/android/api/service/hydra/model/guestservice/GuestServiceStreamCountdownRequest.java", "tv/periscope/android/api/service/hydra/model/guestservice/GuestServiceCallStatusRequest.java", "tv/periscope/android/api/service/hydra/model/guestservice/GuestServiceStreamBaseResponse.java", "tv/periscope/android/api/service/hydra/model/guestservice/GuestServiceStreamPublishRequest.java", "tv/periscope/android/api/service/hydra/model/guestservice/GuestServiceCallRequest.java", "tv/periscope/android/api/service/hydra/model/guestservice/GuestServiceStreamCountdownResponse.java", "tv/periscope/android/api/service/hydra/model/janus/message/JanusResponseHelper.java", "tv/periscope/android/api/service/hydra/model/janus/message/JanusKickBody.java", "tv/periscope/android/api/service/hydra/model/janus/message/JanusRoomDestroyBody.java", "tv/periscope/android/api/service/notifications/model/AutoValue_UnreadNotificationsCountJSONModel.java", "tv/periscope/android/api/service/notifications/model/C$AutoValue_NotificationEventCollectionJSONModel.java", "tv/periscope/android/api/service/notifications/model/ModeratorChannelItemModel.java", "tv/periscope/android/api/service/notifications/model/AutoValue_NotificationEventJSONModel.java", "tv/periscope/android/api/service/notifications/model/C$AutoValue_NotificationEventDataJSONModel.java", "tv/periscope/android/api/service/notifications/model/AutoValue_NotificationIndicatorJSONModel.java", "tv/periscope/android/api/service/notifications/model/C$AutoValue_NotificationEventJSONModel.java", "tv/periscope/android/api/service/notifications/model/AutoValue_NotificationEventCollectionJSONModel.java", "tv/periscope/android/api/service/notifications/model/AutoValue_NotificationEventDataJSONModel.java", "tv/periscope/android/api/service/notifications/model/AutoValue_NotificationEventDetailJSONModel.java", "tv/periscope/android/api/service/notifications/model/C$AutoValue_NotificationEventDetailJSONModel.java", "tv/periscope/android/ui/broadcast/cr.java", "tv/periscope/android/ui/broadcast/aw.java", "tv/periscope/android/ui/broadcaster/prebroadcast/b.java", "tv/periscope/android/hydra/ah.java", "tv/periscope/android/hydra/f.java", "tv/periscope/android/hydra/b.java", "tv/periscope/android/hydra/am.java", "tv/periscope/android/hydra/d.java", "tv/periscope/android/hydra/bn.java", "tv/periscope/android/hydra/bc.java", "tv/periscope/android/hydra/k.java", "tv/periscope/android/hydra/a.java", "tv/periscope/android/hydra/t.java", "tv/periscope/android/hydra/h.java", "tv/periscope/android/video/lhls/LhlsPlaylistParser.java", "org/webrtc/CameraEnumerationAndroid.java", "org/webrtc/HardwareVideoEncoder.java", "org/webrtc/MediaConstraints.java", "org/whispersystems/libsignal/f.java", "org/whispersystems/libsignal/b.java", "de/greenrobot/event/l.java", "de/greenrobot/event/j.java"], "level": "warning", "cvss": 2.3, "cwe": "CWE-327", "owasp": ""}, "App uses SQLite Database and execute raw SQL query. Untrusted user input in raw SQL queries can cause SQL Injection. Also sensitive information should be encrypted and written to the database.": {"path": ["com/evernote/android/job/l.java", "defpackage/$$Lambda$bad$3dsEIN_qF1pGfF819L0jIiDCA.java", "defpackage/$$Lambda$bad$XL_eyVpaefWBdbMjboy07cEDQ8E.java", "defpackage/bab.java", "defpackage/gu.java", "defpackage/glx.java", "defpackage/crb.java", "defpackage/grh.java", "defpackage/hbg.java", "defpackage/gjr.java", "defpackage/gbl.java", "defpackage/hbb.java"], "level": "high", "cvss": 5.9, "cwe": "CWE-89", "owasp": "M7: Client Code Quality"}, "The App uses an insecure Random Number Generator.": {"path": ["com/codahale/metrics/Striped64.java", "com/codahale/metrics/ThreadLocalRandom.java", "defpackage/jrn.java", "defpackage/nsn.java", "defpackage/nrt.java", "defpackage/ma.java", "defpackage/jrl.java", "defpackage/mtq.java", "defpackage/nrj.java", "defpackage/nqi.java", "tv/periscope/android/ui/love/f.java", "tv/periscope/android/ui/love/c.java"], "level": "high", "cvss": 7.5, "cwe": "CWE-330", "owasp": "M5: Insufficient Cryptography"}, "IP Address disclosure": {"path": ["defpackage/mow.java", "defpackage/ml.java", "defpackage/mox.java", "defpackage/mpb.java", "defpackage/mov.java", "defpackage/nrt.java", "defpackage/lh.java", "defpackage/hmd.java", "defpackage/mpf.java", "defpackage/mx.java", "defpackage/nrc.java"], "level": "warning", "cvss": 4.3, "cwe": "CWE-200", "owasp": ""}, "Files may contain hardcoded sensitive informations like usernames, passwords, keys etc.": {"path": ["defpackage/myt.java", "defpackage/nln.java", "defpackage/gbg.java", "defpackage/nmn.java", "defpackage/nsh.java", "tv/periscope/chatman/api/Reporter.java", "tv/periscope/model/c.java", "tv/periscope/model/k.java", "tv/periscope/model/t.java", "tv/periscope/model/user/C$AutoValue_UserJSONModel.java", "tv/periscope/model/chat/c.java", "tv/periscope/model/chat/d.java", "tv/periscope/android/api/ApiRunnable.java", "tv/periscope/android/api/service/hydra/TurnServerResponse.java", "tv/periscope/android/api/service/notifications/model/C$AutoValue_NotificationEventJSONModel.java", "tv/periscope/android/hydra/ah.java", "tv/periscope/android/hydra/t.java", "tv/periscope/android/video/lhls/LhlsPlaylistParser.java"], "level": "high", "cvss": 7.4, "cwe": "CWE-312", "owasp": "M9: Reverse Engineering"}, "MD5 is a weak hash known to have hash collisions.": {"path": ["defpackage/jih.java"], "level": "high", "cvss": 7.4, "cwe": "CWE-327", "owasp": "M5: Insufficient Cryptography"}, "App can read/write to External Storage. Any App can read data written to External Storage.": {"path": ["defpackage/qy.java", "defpackage/lek.java", "defpackage/ezm.java", "defpackage/nox.java", "defpackage/ldy.java", "defpackage/pm.java"], "level": "high", "cvss": 5.5, "cwe": "CWE-276", "owasp": "M2: Insecure Data Storage"}, "This App may have root detection capabilities.": {"path": ["defpackage/loy.java"], "level": "good", "cvss": 0, "cwe": "", "owasp": ""}, "This App copies data to clipboard. Sensitive data should not be copied to clipboard as other applications can access it.": {"path": ["defpackage/cqs.java", "tv/periscope/android/ui/broadcast/br.java"], "level": "info", "cvss": 0, "cwe": "", "owasp": ""}, "App can write to App Directory. Sensitive Information should be encrypted.": {"path": ["tv/periscope/android/hydra/y.java"], "level": "info", "cvss": 3.9, "cwe": "CWE-276", "owasp": ""}}, "exported_count": {"exported_activities": 7, "exported_services": 6, "exported_receivers": 6, "exported_providers": 0}, "trackers": {"detected_trackers": 2, "total_trackers": 285, "trackers": [{"Google CrashLytics": "https://reports.exodus-privacy.eu.org/trackers/27"}, {"Metrics": "https://reports.exodus-privacy.eu.org/trackers/246"}]}, "playstore_details": {"title": "Twitter", "appId": "com.twitter.android", "url": "https://play.google.com/store/apps/details?id=com.twitter.android&hl=en&gl=us", "description": "Join the conversation! Twitter is your go-to social networking app and the source for what's happening in the world. From world news to local news, entertainment to sports and gaming, politics to fun stories that go viral, when it happens in the world, it happens on Twitter first. Find friends or follow influential people - every voice can impact the world! Join over 2 BILLION users worldwide!\nTweet, Retweet, Reply to Tweets, Share or Like - Twitter is Easy to Use\r\nChat privately or go big and initiate a group conversation with anyone who follows you. Track your friends & other Twitter followers or follow your favorite celebrity alongside hundreds of interesting Twitter users, to read their content at a glance. Engage your social network with noteworthy links, photos and videos. Discover which of your Tweets were liked or Retweeted.\r\n\r\nCreate your Free Twitter account Today!\r\nTwitter allows you to find interesting people or build a following of people who are interested in you. Maintaining a social connection has never been easier!Twitter allows celebs to build a personal connection with their fans. This is why Twitter has become one of the most used social media platforms in the world.\r\n\r\nBuild an Engaging Profile\r\nCustomize your profile, add a photo, description, location, and background photo\r\nTweet often and optimize your posting times\r\nPost visual content\r\nUse hashtags in your tweets \r\nDraw in followers outside of Twitter\r\n\r\nKnow What\u2019s Trending Now\r\nDiscover top trending hashtags and breaking news headlines. Whether you\u2019re interested in sports highlights, pop culture and entertainment or politics, Twitter is your source of information.\r\n\r\nLive streaming events\r\nJoin the conversation or watch live videos to deeply engage with large audiences directly from your mobile device. Go Live, create your own live streaming events, share videos or sit back and watch events from around the world.\r\n\r\nPrivacy Policy: https://twitter.com/en/privacy\nTerms and Conditions: https://twitter.com/en/tos", "summary": "Breaking news, entertainment, sports, politics and everything in-between!", "summaryHTML": "Breaking news, entertainment, sports, politics and everything in-between!", "installs": "500,000,000+", "minInstalls": 500000000, "score": 4.5165668, "ratings": 14719223, "reviews": 3835462, "histogram": [786018, 215675, 527090, 2270480, 10919957], "price": 0, "free": true, "currency": "USD", "offersIAP": null, "size": "Varies with device", "androidVersion": "Varies", "androidVersionText": "Varies with device", "developer": "Twitter, Inc.", "developerId": "Twitter,+Inc.", "developerEmail": "google-play-emails@twitter.com", "developerWebsite": "https://support.twitter.com/articles/20169915", "developerAddress": "Twitter, Inc.\n1355 Market Street, Suite 900\nSan Francisco, CA 94103", "privacyPolicy": "http://twitter.com/privacy", "developerInternalID": "7022973042396704692", "genre": "News & Magazines", "genreId": "NEWS_AND_MAGAZINES", "icon": "https://lh3.googleusercontent.com/wIf3HtczQDjHzHuu7vezhqNs0zXAG85F7VmP7nhsTxO3OHegrVXlqIh_DWBYi86FTIGk", "headerImage": "https://lh3.googleusercontent.com/nYUZyNKkZC4gGEeny_-ZrGQobnNRUwaJUFKa95gcTHoMTIZcuBSr6V8CeD9fvBkZ_g", "screenshots": ["https://lh3.googleusercontent.com/DfAVURLgv0F8OZxFds3vLqd6o7dW9hbe9AUPgvVi4kzY5qb7Y-VRitHYA8_9W8edidI", "https://lh3.googleusercontent.com/hwGHMxXtelMVMux5Zu-Qc9e_pv2hjIxz7ZEvcN2MO6Cngfmhf4zuUPIbrT7M_8pxGps", "https://lh3.googleusercontent.com/y7QNQRs8UrKFPTc8AETAl04rjhzliVeuIZhy3PxHcpmH4j-sGqtPp-E1WEQnLPNZILQ", "https://lh3.googleusercontent.com/ce34ODRANNyI2kIJFdcaf0m4U3JKNpWZk3J5OlpVFZDV_KekO0G-uwtg-KIYVff6k5Y", "https://lh3.googleusercontent.com/hQ8bd5RHkFFThA-GMC6QUoNglvPmKpKOYrxP5qPe8qj2tLCF6tfo34JaMJ6fu1itvBc", "https://lh3.googleusercontent.com/62WZ2iowszu44BA0cCNxBJIbkt8vxDt6j46QLhYyiJCx9mN27VEP52Gk_bTDtRVZmR0", "https://lh3.googleusercontent.com/5WpsYnci94A-Vq0H55VwZwqDRLM-6ML17wsDj5ydS77Sx4wVYVGULw4z8kZ5Hl383-Y", "https://lh3.googleusercontent.com/U4x4fAneKu3o_I0VajXc66haEZGsP6qXcPttEzQk439mWggCZhidZiFeNc1VvqU-nbk", "https://lh3.googleusercontent.com/TlPyybF6PAJ0ZDDFJ4ZQ-UhwctkOk9oPtorSwluuOC23lxKETZ_XaHh0HzD_Ss-YVHU", "https://lh3.googleusercontent.com/PJOoG-EGN4bGp-iIEfvE4zXTajNycQi4lXpQTAasZ14b6UEhbuQagiTm3amxPCYQxUI"], "video": "https://www.youtube.com/embed/AUBvHej0hrk?ps=play&vq=large&rel=0&autohide=1&showinfo=0", "videoImage": "https://i.ytimg.com/vi/AUBvHej0hrk/hqdefault.jpg", "contentRating": "Mature 17+", "contentRatingDescription": null, "adSupported": true, "containsAds": true, "released": "Apr 30, 2010", "updated": 1583343546, "version": "Varies with device", "recentChanges": "Get ready for the new dark mode, now with 2 options \u2013 dim and lights out \u2013 and an automatic setting!", "recentChangesHTML": "Get ready for the new dark mode, now with 2 options \u2013 dim and lights out \u2013 and an automatic setting!", "error": false}, "average_cvss": 5.7, "security_score": 10}